risk_compliance/__init__.py
risk_compliance/consul_support.py
risk_compliance/data_support.py
risk_compliance/email_support.py
risk_compliance/spark_support.py
risk_compliance-2023.1.31.dist-info/METADATA
risk_compliance-2023.1.31.dist-info/WHEEL
risk_compliance-2023.1.31.dist-info/top_level.txt
risk_compliance-2023.1.31.dist-info/RECORD
