Metadata-Version: 2.1
Name: risk-compliance
Version: 2023.1.31
Summary: A package for risk compliance.
Author: brown_hui
Author-email: brown_hui@163.com
Keywords: risk
